logargparser.py
logargparser-0.1.0.dist-info/LICENSE.md
logargparser-0.1.0.dist-info/METADATA
logargparser-0.1.0.dist-info/WHEEL
logargparser-0.1.0.dist-info/RECORD
